Metadata-Version: 2.1
Name: dagrules
Version: 0.1.0
Summary: dagrules - dbt DAG rule creator and validator
Home-page: https://github.com/gnilrets/dagrules
Author: Sterling Paramore
Author-email: gnilrets@gmail.com
License: MIT
Keywords: dbt dag
Platform: UNKNOWN
Classifier: Development Status :: 3 - Alpha
Classifier: Intended Audience :: Developers
Classifier: Topic :: Software Development :: Libraries :: Python Modules
Classifier: License :: OSI Approved :: MIT License
Classifier: Programming Language :: Python :: 3
Classifier: Programming Language :: Python :: 3.8
Requires-Python: >=3
Provides-Extra: dev
Provides-Extra: test
License-File: LICENSE.txt
